fastjango/__init__.py
fastjango/http.py
fastjango/urls.py
fastjango/templates/app_template/__init__.py
fastjango/templates/app_template/models.py
fastjango/templates/app_template/routes.py
fastjango/templates/app_template/schemas.py
fastjango/templates/app_template/services.py
fastjango/templates/app_template/tests/__init__.py
fastjango/templates/app_template/tests/test_models.py
fastjango/templates/app_template/tests/test_routes.py
fastjango/templates/project_template/manage.py
fastjango/templates/project_template/requirements.txt
fastjango/templates/project_template/{{project_name}}/__init__.py
fastjango/templates/project_template/{{project_name}}/asgi.py
fastjango/templates/project_template/{{project_name}}/settings.py
fastjango/templates/project_template/{{project_name}}/urls.py
fastjango/templates/project_template/{{project_name}}/wsgi.py
fastjango/templates/project_template/{{project_name}}/api/__init__.py
fastjango/templates/project_template/{{project_name}}/api/urls.py
fastjango-0.1.1.dist-info/licenses/LICENSE
fastjango-0.1.1.dist-info/METADATA
fastjango-0.1.1.dist-info/WHEEL
fastjango-0.1.1.dist-info/entry_points.txt
fastjango-0.1.1.dist-info/top_level.txt
fastjango-0.1.1.dist-info/RECORD
