Metadata-Version: 2.4
Name: fastjango
Version: 0.1.1
Summary: A fastweb framework inspired by Django using FastAPI as core
Home-page: https://github.com/fastjango/fastjango
Author: Bhavik Shah
Author-email: Bhavik Shah - FastJango Team <bhavik1st@gmail.com>
License: MIT License
Project-URL: Documentation, https://github.com/fastjango/fastjango
Project-URL: Source, https://github.com/fastjango/fastjango
Project-URL: Tracker, https://github.com/fastjango/fastjango/issues
Keywords: fastapi,django,web framework
Classifier: Development Status :: 3 - Alpha
Classifier: Environment :: Web Environment
Classifier: Framework :: FastAPI
Classifier: Intended Audience :: Developers
Classifier: License :: OSI Approved :: MIT License
Classifier: Programming Language :: Python :: 3
Classifier: Programming Language :: Python :: 3.8
Classifier: Programming Language :: Python :: 3.9
Classifier: Programming Language :: Python :: 3.10
Classifier: Topic :: Internet :: WWW/HTTP
Classifier: Topic :: Software Development :: Libraries :: Application Frameworks
Requires-Python: >=3.8
License-File: LICENSE
Requires-Dist: fastapi<0.101.0,>=0.100.0
Requires-Dist: uvicorn<0.24.0,>=0.23.0
Requires-Dist: jinja2<3.2.0,>=3.1.2
Requires-Dist: python-multipart<0.0.7,>=0.0.6
Requires-Dist: pydantic<3.0.0,>=2.0.0
Requires-Dist: typer<0.10.0,>=0.9.0
Requires-Dist: rich<13.5.0,>=13.4.0
Requires-Dist: sqlalchemy<2.1.0,>=2.0.19
Requires-Dist: alembic<1.12.0,>=1.11.1
Provides-Extra: dev
Requires-Dist: pytest<7.5.0,>=7.4.0; extra == "dev"
Requires-Dist: pytest-cov<4.2.0,>=4.1.0; extra == "dev"
Requires-Dist: black<23.8.0,>=23.7.0; extra == "dev"
Requires-Dist: isort<5.13.0,>=5.12.0; extra == "dev"
Requires-Dist: flake8<6.2.0,>=6.1.0; extra == "dev"
Requires-Dist: httpx<0.25.0,>=0.24.1; extra == "dev"
Provides-Extra: docs
Requires-Dist: mkdocs<1.6.0,>=1.5.2; extra == "docs"
Requires-Dist: mkdocs-material<9.3.0,>=9.2.7; extra == "docs"
Requires-Dist: mkdocstrings<0.24.0,>=0.23.0; extra == "docs"
Requires-Dist: mkdocstrings-python<1.7.0,>=1.6.0; extra == "docs"
Dynamic: author
Dynamic: home-page
Dynamic: license-file
Dynamic: requires-python
